pyagentai/__init__.py
pyagentai/api_methods/__init__.py
pyagentai/api_methods/company_financial_info.py
pyagentai/api_methods/company_financial_profile.py
pyagentai/api_methods/domain_info.py
pyagentai/api_methods/find_agents.py
pyagentai/api_methods/find_linkedin_profile.py
pyagentai/api_methods/get_bluesky_posts.py
pyagentai/api_methods/get_company_object.py
pyagentai/api_methods/get_google_news.py
pyagentai/api_methods/get_instagram_followers.py
pyagentai/api_methods/get_instagram_profile.py
pyagentai/api_methods/get_linkedin_activity.py
pyagentai/api_methods/get_linkedin_profile.py
pyagentai/api_methods/get_recent_tweets.py
pyagentai/api_methods/get_search_results.py
pyagentai/api_methods/get_twitter_users.py
pyagentai/api_methods/get_youtube_channel.py
pyagentai/api_methods/get_youtube_transcript.py
pyagentai/api_methods/grab_web_screenshot.py
pyagentai/api_methods/grab_web_text.py
pyagentai/api_methods/run_youtube_search.py
pyagentai/api_methods/search_bluesky_posts.py
pyagentai/client.py
pyagentai/client.pyi
pyagentai/config/__init__.py
pyagentai/config/agentai_config.py
pyagentai/config/agentai_endpoints.py
pyagentai/types/__init__.py
pyagentai/types/agent_info.py
pyagentai/types/url_endpoint.py
pyagentai/utils/__init__.py
pyagentai/utils/logger.py
pyagentai/utils/method_registrar_mixin.py
pyagentai/utils/text_processor.py
pyagentai-0.1.2.dist-info/LICENSE
pyagentai-0.1.2.dist-info/METADATA
pyagentai-0.1.2.dist-info/WHEEL
pyagentai-0.1.2.dist-info/RECORD
