Metadata-Version: 2.3
Name: pyagentai
Version: 0.1.2
Summary: A Python library for seamless integration with Agent.ai APIs
License: GPL-3.0-only
Author: MeepoLabs
Author-email: developers@meepolabs.com
Requires-Python: >=3.10,<4.0
Classifier: Development Status :: 3 - Alpha
Classifier: Intended Audience :: Developers
Classifier: License :: OSI Approved :: GNU General Public License v3 (GPLv3)
Classifier: Programming Language :: Python :: 3
Classifier: Programming Language :: Python :: 3.10
Classifier: Programming Language :: Python :: 3.11
Classifier: Programming Language :: Python :: 3.12
Classifier: Programming Language :: Python :: 3.13
Classifier: Topic :: Scientific/Engineering :: Artificial Intelligence
Classifier: Topic :: Software Development :: Libraries :: Python Modules
Requires-Dist: httpx[http2] (>=0.28.1,<0.29.0)
Requires-Dist: pydantic (>=2.10.6,<3.0.0)
Requires-Dist: structlog (>=25.2.0,<26.0.0)
Requires-Dist: typing-extensions (>=4.8.0,<5.0.0)
Project-URL: Documentation, https://pyagentai.readthedocs.io
Project-URL: Repository, https://github.com/meepolabs/pyagentai
